TNSA/__init__.py
TNSA/tnsamcv.py
TNSAMCV-0.1.0.dist-info/METADATA
TNSAMCV-0.1.0.dist-info/WHEEL
TNSAMCV-0.1.0.dist-info/top_level.txt
TNSAMCV-0.1.0.dist-info/RECORD
