Metadata-Version: 2.1
Name: TNSAMCV
Version: 0.1.0
Summary: TNSAMCV is a module by TNSA which is used in computer vision
Home-page: UNKNOWN
Author: TNSA
Author-email: thishyakethabimalla@gmail.com
License: UNKNOWN
Platform: UNKNOWN
